README.md
setup.py
memproxy/__init__.py
memproxy/item.py
memproxy/memproxy.py
memproxy/py.typed
memproxy/redis.py
memproxy/session.py
memproxy.egg-info/PKG-INFO
memproxy.egg-info/SOURCES.txt
memproxy.egg-info/dependency_links.txt
memproxy.egg-info/requires.txt
memproxy.egg-info/top_level.txt
memproxy/proxy/__init__.py
memproxy/proxy/proxy.py
memproxy/proxy/py.typed
memproxy/proxy/replicated.py
memproxy/proxy/route.py
memproxy/proxy/stats.py
test/test_item.py
test/test_redis.py
test/test_session.py