Metadata-Version: 2.1
Name: memproxy
Version: 0.3.0rc21
Summary: A library for strong consistent caching
Home-page: https://github.com/QuangTung97/memproxy-py
Author: quangtung97
Author-email: quangtung29121997@gmail.com
License: MIT
Project-URL: Changes, https://github.com/QuangTung97/memproxy-py/releases
Project-URL: Code, https://github.com/QuangTung97/memproxy-py
Project-URL: Issue Tracker, https://github.com/QuangTung97/memproxy-py/issues
Keywords: Redis,key-value store,caching
Platform: UNKNOWN
Classifier: Programming Language :: Python :: 3
Classifier: License :: OSI Approved :: MIT License
Classifier: Operating System :: OS Independent
Requires-Python: >=3.7
